mdformat_beautysh/__init__.py
mdformat_beautysh-1.0.0.dist-info/METADATA
mdformat_beautysh-1.0.0.dist-info/WHEEL
mdformat_beautysh-1.0.0.dist-info/entry_points.txt
mdformat_beautysh-1.0.0.dist-info/licenses/LICENSE
mdformat_beautysh-1.0.0.dist-info/RECORD
