Metadata-Version: 2.4
Name: mdformat-beautysh
Version: 1.0.0
Summary: Mdformat plugin to beautify Bash scripts
License: MIT
License-File: LICENSE
Keywords: mdformat,beautysh,bash,markdown,commonmark,formatter
Author: Taneli Hukkinen
Author-email: hukkin@users.noreply.github.com
Requires-Python: >=3.10
Classifier: License :: OSI Approved :: MIT License
Classifier: Programming Language :: Python :: 3
Classifier: Programming Language :: Python :: 3.10
Classifier: Programming Language :: Python :: 3.11
Classifier: Programming Language :: Python :: 3.12
Classifier: Programming Language :: Python :: 3.13
Classifier: Programming Language :: Python :: 3.14
Classifier: Topic :: Documentation
Classifier: Topic :: Text Processing :: Markup
Requires-Dist: beautysh (>=6.3.0)
Requires-Dist: mdformat (>=0.3.0)
Project-URL: Repository, https://github.com/hukkin/mdformat-beautysh
